[
    {
        "cid": "1223842185",
        "comment": " 在类型片上达到了非常高的水准，画面演技打斗设计用心度。。。都够好，如果有些地方再含蓄一点再、再弱化一些就好了，还有很多其它问题，但是整个观影过程够畅快。思想上比较驳杂，有点圆滑,也有局限，但绝不是许多豆瓣ER所谓的政教宣传意淫，反而在朝好莱坞类似类型片标准靠拢，但脸皮可比后者薄多了\n        ",
        "star": "推荐",
        "vote": "4"
    },
    {
        "cid": "1232100524",
        "comment": " 一部让人热血沸腾的影片，有些bug还是放过比较好。\n        ",
        "star": "推荐",
        "vote": "0"
    },
    {
        "cid": "1227456606",
        "comment": " 这是一部吴京导演的个人秀 然而张翰的出现无疑是这个电影最失败的地方 没有之一 开篇镜头很厉害 广电总局也变了 现在脏话血腥镜头都可以有 不是很懂 不过整体不错 吴京的鲨鱼线很厉害。。。\n        ",
        "star": "还行",
        "vote": "1"
    },
    {
        "cid": "1225024479",
        "comment": " 看完电影还好……但看完片头的征兵广告，隐隐担心了一下印度出差\n        ",
        "star": "还行",
        "vote": "0"
    },
    {
        "cid": "1225102810",
        "comment": " 东来：达康书记，我派人来救你啦！张瀚：爸爸，我想当兵！够热血够主旋律够直男，吴京挑女主角的眼光也还是不错的。\n        ",
        "star": "推荐",
        "vote": "3"
    },
    {
        "cid": "1223473369",
        "comment": " 不得不说与目前大部分国产片相比，战狼2确实进步很大，很多地方可以看出向好莱坞大片学习的痕迹。可是电影没有把重点放在保护活体疫苗黑人小女孩身上，却变成了爱国主旋律和吴京个人秀，总是有些可惜的。相比较而言，像《辛德勒名单》这样伟大电影，弘扬人性以小见大，显然更加高明。\n        ",
        "star": "还行",
        "vote": "7"
    },
    {
        "cid": "1223934327",
        "comment": " 墙国无敌........\n        ",
        "star": "很差",
        "vote": "25"
    },
    {
        "cid": "1225714776",
        "comment": " 观影感受和看速激系列一个效果，全程对铁血硬汉的柔情戏，抒情戏码以及燃的不知所谓的bgm坐立难安。\n感受到的爱国情怀给你一星，动作再给一星。\n但终究是电影。就电影来论电影，实在说别的。\n不如剔除所有，只留动作戏才好。\n\n\n        ",
        "star": "较差",
        "vote": "3"
    },
    {
        "cid": "1227272903",
        "comment": " 太吵了太假了…不过不难看\n        ",
        "star": "还行",
        "vote": "4"
    },
    {
        "cid": "1226256382",
        "comment": " 国产动作片最佳摄影\n        ",
        "star": "推荐",
        "vote": "8"
    },
    {
        "cid": "1227965704",
        "comment": " 张瀚承包了所有的笑点，叉骨大大和吴京的打戏真是帅。\n        ",
        "star": "推荐",
        "vote": "0"
    },
    {
        "cid": "1226070079",
        "comment": " 为什么打五星，因为哥也是中国人！\n        ",
        "star": "力荐",
        "vote": "4"
    },
    {
        "cid": "1226082246",
        "comment": " 为中国情怀五星，个人英雄主义还是很明显的，但是燃那！热血那！尤其最后中国护照出现那点真的挺热泪盈眶的。我们不是出生在和平时代，但是我们生活在和平的中国。\n                \n                \n",
        "star": "力荐",
        "vote": "5"
    },
    {
        "cid": "1225182847",
        "comment": " 很不错的国产电影，略显夸张，不过7分加还是没问题的~那些导弹制导的精度没有问题吗…\n        ",
        "star": "推荐",
        "vote": "2"
    },
    {
        "cid": "1225113740",
        "comment": " 谁tm敢说不好看，削他哦！\n        ",
        "star": "力荐",
        "vote": "3"
    },
    {
        "cid": "1221641399",
        "comment": " 跟第一部一样，看得热血沸腾，一直觉得吴京的打戏很有美感，张瀚的演技可圈可点～（ps：看彩蛋，这是第三部预定的节奏～😄）\n        ",
        "star": "力荐",
        "vote": "11"
    },
    {
        "cid": "1221532822",
        "comment": " 武打干净利落，好久没看得这么舒爽了。吴京台词功力太好了，冷锋帅到爆棚！张瀚希望他不要总是翻白眼了，熊孩子那里表情挺好的，整部剧可爱担当吧2333(ps他好白啊)达康书记感觉不太适合这个角色，演技台词都很好，但是就是没有觉得特别好(囧没有形容词)给一星毒说是小粉红的，门在那，走吧。\n        ",
        "star": "推荐",
        "vote": "20"
    },
    {
        "cid": "1234939611",
        "comment": " 凑热闹剧，竟然还二刷了，哈哈哈\n        ",
        "star": "未评分",
        "vote": "0"
    },
    {
        "cid": "1229305521",
        "comment": " 就爆米花电影吧，从头打到尾。\n        ",
        "star": "还行",
        "vote": "3"
    },
    {
        "cid": "1232387525",
        "comment": " 比1好，经典桥段较多，剧情BUG也在可接受范围，就是BOSS和1长得差不多难道吴京这么喜欢络腮胡的对手？票房火成这样有点意外，如果不是注水的话，我觉得从众心理还是占大部分，当然能把《美人鱼》《捉妖记》这种片拉下马还是值得赞赏。\n        ",
        "star": "推荐",
        "vote": "0"
    }
]