[
    {
        "cid": "1231078373",
        "comment": " 傻逼电影就是在中国特别有市场\n        ",
        "star": "很差",
        "vote": "18"
    },
    {
        "cid": "1225208310",
        "comment": " 感觉很值票价的电影，总在大荧幕看美国人拯救世界，这次终于看到我们中国人做主角了，剧情有点用力过猛，毕竟我们还在发展期自信心塑造中，期待有一天我们能自然而然演出老子天下第一的气势。打斗很精彩，爱情戏安排了个美国混血儿有点怪怪的。达康书记和张瀚演的也都很好，看得很燃\n        ",
        "star": "力荐",
        "vote": "21"
    },
    {
        "cid": "1225865163",
        "comment": " 不敢评论\n        ",
        "star": "较差",
        "vote": "17"
    },
    {
        "cid": "1229145454",
        "comment": " 片尾出现护照和那句话，只能打负分。作为一个真的在国外遇见过危险并且曾经相信这句话去大使馆求救的人，奉劝各位别做梦了。\n        ",
        "star": "很差",
        "vote": "3"
    },
    {
        "cid": "1222749999",
        "comment": " 据说打一星就会有人来骂？\n        ",
        "star": "很差",
        "vote": "31"
    },
    {
        "cid": "1230891267",
        "comment": " 直男癌…小粉红…\n        ",
        "star": "较差",
        "vote": "10"
    },
    {
        "cid": "1225099076",
        "comment": " 电影三星半。半星，表个态度支持拍摄这类片。。这电影看到最后真的太红了。。美分肯定坐不住。。。电影角度讲，只要不存在对大陆偏见，对美帝爆米花好半星没问题。香港动作团队宇宙第一谁黑的了？更何况吴京是实打实的打。。但总体也没太好也就是了。。美帝维和世界这么多年够了，该中国了\n        ",
        "star": "推荐",
        "vote": "4"
    },
    {
        "cid": "1226907097",
        "comment": " 剧本的政治红线踩得很稳，有中国动作片类型的雏形，虽然土酷里主要是土，也建议出口到美国。此片主要算一个大幽默\n        ",
        "star": "还行",
        "vote": "2"
    },
    {
        "cid": "1224011402",
        "comment": " 不功不过的合格商业片，几位配角都看着舒服极了，卢靖姗的美也是很高级的一种，整体来说超出预期，豆瓣评分的调节机制确实挺科学，有黑有吹但最终给出的分数足够公正。\n        ",
        "star": "推荐",
        "vote": "13"
    },
    {
        "cid": "1225519360",
        "comment": " 打得很努力了，不困。被吴京圈粉了。\n        ",
        "star": "还行",
        "vote": "6"
    },
    {
        "cid": "1223538087",
        "comment": " 没什么景深镜头，不用看imax。各种梗还是挺顺的，节奏也中规中矩，虽然后面圆得不好。豆瓣上一堆看都不看就跟风打一星可以说很情绪化了。\n        ",
        "star": "还行",
        "vote": "3"
    },
    {
        "cid": "1223289340",
        "comment": " 场面堪称国产枪战动作片新标杆，文戏也可圈可点不出戏，最后一个镜头减一星。\n        ",
        "star": "推荐",
        "vote": "2"
    },
    {
        "cid": "1226379183",
        "comment": " 弹簧床垫截火箭是几个意思？\n        ",
        "star": "还行",
        "vote": "8"
    },
    {
        "cid": "1221623607",
        "comment": " 一人挑一个军队，硬扯无聊的爱情线，唯一的两分给你的硬汉，也太过了。\n        ",
        "star": "较差",
        "vote": "111"
    },
    {
        "cid": "1223164723",
        "comment": " 动作片还是挺不错的，当然本来中间大家围起冷锋也就一枪的事儿，莫名其妙就撤了也是作死。不过打的精彩剧情也不错，对一部电影你还想要求什么呢？\n        ",
        "star": "推荐",
        "vote": "9"
    },
    {
        "cid": "1224639844",
        "comment": " 战狼2：我很好看。\n        ",
        "star": "很差",
        "vote": "11"
    },
    {
        "cid": "1223692283",
        "comment": " 坦克漂移技术哪家强，首选支那红战狼。\n        ",
        "star": "较差",
        "vote": "29"
    },
    {
        "cid": "1222098644",
        "comment": " 超赞！！！热血沸腾，激情四射，666！！！\n                \n                \n",
        "star": "力荐",
        "vote": "12"
    },
    {
        "cid": "1224216685",
        "comment": " 作为动作片是ok的，开场水下戏不错\n        ",
        "star": "较差",
        "vote": "3"
    },
    {
        "cid": "1226273197",
        "comment": " 死磕，野心，类型化的努力很明晰。男主角/导演不死之躯，“中国人民的好朋友”等国际主义杂牌咸鱼人物，肉身化作国旗旗杆的仪式，都很实诚地把魔幻主旋律一路尬到底。\n        ",
        "star": "较差",
        "vote": "10"
    }
]